my_lib_api/__init__.py
my_lib_api/main.py
my_lib_api/run_app.py
my_lib_api/templates/import_file.html
my_lib_api-0.1.dist-info/METADATA
my_lib_api-0.1.dist-info/WHEEL
my_lib_api-0.1.dist-info/top_level.txt
my_lib_api-0.1.dist-info/RECORD
